backtester.py
core/*.py
core/__init__.py
core/__main__.py
core/backtest.py
core/engine.py
core/entries.py
core/exits.py
core/exits_atr.py
core/filters.py
core/report.py
core/sizing.py
core/strategy.py
core/walk.py
cryptolion/__init__.py
cryptolion/__main__.py
cryptolion/backtest.py
cryptolion/backtester.py
cryptolion/cli.py
cryptolion/engine.py
cryptolion/entries.py
cryptolion/exits.py
cryptolion/exits_atr.py
cryptolion/exits_base.py
cryptolion/exits_more.py
cryptolion/filters.py
cryptolion/filters_extended.py
cryptolion/report.py
cryptolion/strategy.py
cryptolion/strategy_base.py
cryptolion/ultra.py
cryptolion/walk.py
cryptolion/filters/__init__.py
cryptolion/filters/extended.py
cryptolion/filters/volume.py
cryptolion/strategies/__init.__.py
cryptolion/strategies/base.py
cryptolion/strategies/ultra.py
cryptolion-0.1.2.dist-info/METADATA
cryptolion-0.1.2.dist-info/WHEEL
cryptolion-0.1.2.dist-info/top_level.txt
cryptolion-0.1.2.dist-info/RECORD
