Metadata-Version: 2.4
Name: cryptolion
Version: 0.1.2
Summary: CryptoLion back-testing library
Requires-Python: >=3.9
Requires-Dist: pandas>=1.3
Requires-Dist: numpy>=1.21
Provides-Extra: dev
Requires-Dist: pytest; extra == "dev"
Requires-Dist: coverage; extra == "dev"
Requires-Dist: sphinx; extra == "dev"
Requires-Dist: bump2version; extra == "dev"
Requires-Dist: twine; extra == "dev"
